<annotation>
  <folder></folder>
  <filename>Datacluster Hindi Text Data (43).jpg</filename>
  <source>
    <database>Unknown</database>
    <annotation>Unknown</annotation>
    <image>Unknown</image>
  </source>
  <size>
    <width>2448</width>
    <height>3264</height>
    <depth></depth>
  </size>
  <segmented>0</segmented>
  <object>
    <name>text</name>
    <truncated>0</truncated>
    <occluded>0</occluded>
    <difficult>0</difficult>
    <bndbox>
      <xmin>669.7</xmin>
      <ymin>1267.34</ymin>
      <xmax>1259.77</xmax>
      <ymax>2343.82</ymax>
    </bndbox>
    <attributes>
      <attribute>
        <name>rotation</name>
        <value>0.0</value>
      </attribute>
    </attributes>
  </object>
  <object>
    <name>text</name>
    <truncated>0</truncated>
    <occluded>0</occluded>
    <difficult>0</difficult>
    <bndbox>
      <xmin>1327.5</xmin>
      <ymin>12.0</ymin>
      <xmax>1857.8</xmax>
      <ymax>3252.9</ymax>
    </bndbox>
    <attributes>
      <attribute>
        <name>rotation</name>
        <value>0.0</value>
      </attribute>
    </attributes>
  </object>
</annotation>
